LICENSE
MANIFEST.in
README.rst
setup.py
ludolph_zabbix/__init__.py
ludolph_zabbix/zapi.py
ludolph_zabbix.egg-info/PKG-INFO
ludolph_zabbix.egg-info/SOURCES.txt
ludolph_zabbix.egg-info/dependency_links.txt
ludolph_zabbix.egg-info/requires.txt
ludolph_zabbix.egg-info/top_level.txt